openpyxl_table/__init__.py
openpyxl_table/py.typed
openpyxl_table-1.2.7.dist-info/METADATA
openpyxl_table-1.2.7.dist-info/WHEEL
openpyxl_table-1.2.7.dist-info/licenses/LICENSE
openpyxl_table-1.2.7.dist-info/RECORD
